{"o3QLiIkNA5ls/vGOwn0nZQ==":"mbr-1920x1276.jpg","aNZuxfRj9zTvkogiWP4SHg==":"logo_bluebrown-218x128.png","lw1/Dizk/WiPw1cWVOJ5Qw==":"logo_bluebrown-128x75.png","jaH8hDMPUwhDrtrquoC5YA==":"158267-017-099f-1400x2100.jpeg","5FjcoRtCqdr6pielKUjWRQ==":"158267-017-099f-1-1400x2100.jpeg","qsSWYrVUfzL+njF3QkhPIA==":"screen%20shot%202020-04-07%20at%203.05.18%20pm-552x308.png","cxNBkinls1xz+lchF5Buug==":"screen%20shot%202020-04-07%20at%203.05.26%20pm-370x476.png","2enz7otsWIDgq6pG3wiiDg==":"screen%20shot%202019-12-16%20at%2011.58.39%20am-750x1124.png","hkf8khpsp5W3erYLtLaiVw==":"screen%20shot%202019-12-16%20at%2012.08.12%20pm-1124x738.png","QgTY58ytgBlYnb4Yi7hL6Q==":"screen%20shot%202019-12-16%20at%2012.03.56%20pm-1128x742.png","jwfyhBse6TysAE44S/RFDw==":"screen%20shot%202019-12-16%20at%2012.03.56%20pm-1128x742.png","WQGTy/Rf4EVZJY/uBRASdw==":"screen%20shot%202019-12-16%20at%2011.56.16%20am-1124x758.png","2750szx6Gl8rHukGZJVhuA==":"ccs_logo_color-834x834.png","AxSxTsyoGWb5zzF0h2uumw==":"screen%20shot%202020-05-06%20at%205.44.55%20pm-770x590.png","cU673ddvIsW+3H+uavwmug==":"screen%20shot%202020-05-06%20at%205.45.05%20pm-770x592.png","UL9W2Dl3YVIix+9DrRf+aA==":"ccs_logo_bw-834x834.png"}